{
    "1": {
        "quiet": "тихий, спокійний",
        "quite": "досить, доволі",
        "typical": "типовий",
        "resident": "житель",
        "avenue": "проспект",
        "to look gloomy": "виглядати похмуро",
        "in fact": "насправді, фактично",
        "to lead life": "вести життя",
        "suburb": "околиця",
        "suburban": "околичний",
        "to look after": "доглядати",
        "carefully": "дбайливо",
        "regularly": "регулярно",
        "to feed-fed-fed": "годувати",
        "daily": "щоденно",
        "tinned": "консервований",
        "supply": "запас",
        "fresh water": "прісна вода",
        "plenty of": "достатньо",
        "carpet space": "килимовий настил",
        "to put practice": "грати гольф",
        "comfortable": "комфортний, зручний",
        "to be content with": "бути задоволеним",
        "to be fond of": "захоплюватись",
        "local": "місцевий",
        "vet = veterinarian": "ветеринар",
        "to go blind": "сліпнути",
        "to go deaf": "глухнути",
        "however": "проте, однак",
        "to be confident of": "бути впевненим у",
        "to cure": "лікувати (хірургічно)",
        "to treat": "лікувати (терапевтично)",
        "by means of": "за допомогою",
        "to give an injection": "вводити ін’єкцію",
        "so that": "так, що",
        "peacefully": "мирно, спокійно",
        "the whole time/all the time/the entire time": "весь час",
        "even": "навіть",
        "pretty": "симпатична",
        "handsome": "симпатичний",
        "nurse": "медсестра",
        "to stand by": "поруч",
        "to comfort": "заспокоїти",
        "in case": "у випадку якщо",
        "lonely": "самотній",
        "strange": "чужий",
        "surroundings": "оточення",
        "in general": "загалом",
        "both…and…": "обидва, і…і",
        "desire": "бажання",
        "adventurous": "авантюрний, ризикований"
    },
    "2": {
        "Why the rush?": "Чому поспішаєш?",
        "to be on the way to": "бути на шляху до",
        "to have brunch": "перекусити",
        "to be off to": "відправлятись",
        "at least": "принаймні",
        "fortnight": "два тижні",
        "perhaps\\possibly\\probably\\maybe": "можливо",
        "to arrange": "організовувати",
        "to go on": "продовжувати",
        "to be on": "йти (на сцені, на екрані)",
        "play": "вистава, п’єса",
        "to book": "бронювати",
        "seat": "місце",
        "to make sure": "запевнитись",
        "to ring\\to call\\to phone": "брякнути, подзвонити, зателефонувати",
        "to confirm": "підтверджувати",
        "I must fly now": "змушений бігти",
        "to wait around": "чекати без діла",
        "to spoil-spoilt-spoilt": "псувати",
        "to upset": "засмутити",
        "to give regards to smb": "передавати комусь вітання"
    },
    "3": {
        "to wake up -woke-woken": "прокидатись, будити",
        "quarter to": "за чверть",
        "quarter past": "чверть по",
        "actually": "в принципі, взагалі-то",
        "to shine-shone-shone": "сяяти",
        "lately": "останнім часом",
        "to think/believe/expect/guess/regard/consider": "вважати",
        "to suppose": "припускати",
        "to put sth off": "відкладати щось",
        "Never put it off till tomorrow what you can do today.": "Ніколи не відкладай на завтра те, що можна зробити сьогодні",
        "to postpone": "переносити (зустріч)",
        "lovely": "милий",
        "spot": "пляма, місце",
        "bend": "вигин, поворот",
        "just before you get to": "не доїжджаючи до",
        "to walk across": "пересікати",
        "to walk along": "йти вздовж",
        "to walk through": "йти через (ліс, парк)",
        "to go over": "йти через (міст)",
        "to go past = to pass": "йти повз",
        "elm tree": "в’яз",
        "it’s a pity": "шкода, що",
        "to mention": "зазначити",
        "Right then.": "Тоді гаразд.",
        "in about an hour": "приблизно через годину"
    },
    "5": {
        "to be good at": "добре у чомусь розбиратись",
        "to decide": "вирішувати",
        "decision": "рішення",
        "decisive": "рішучий",
        "to take degree in": "здобувати ступінь з",
        "secondary school": "середня школа",
        "by chance": "випадково",
        "to offer": "пропонувати (свої послуги)",
        "to suggest": "пропонувати (зробити щось разом)",
        "foreign": "іноземний",
        "foreigner": "іноземець",
        "during": "під час, впродовж",
        "adult": "дорослий",
        "immensely": "надзвичайно, неймовірно",
        "to enjoy": "насолоджуватись",
        "to find out": "дізнатись",
        "to be interested in": "бути зацікавленим у",
        "own language": "рідна мова",
        "since": "з того часу, від тоді",
        "to specialise in": "спеціалізуватись на",
        "advantages": "переваги",
        "disadvantages": "недоліки",
        "pros and cons": "за і проти",
        "to enable": "робити можливим",
        "almost = nearly": "майже",
        "anywhere": "будь де",
        "to spend time / money": "проводити час, витрачати гроші",
        "to waste time / money": "марно тратити час, гроші",
        "yet": "ще (в запитаннях – вже)",
        "to intend": "мати намір",
        "women": "жінки",
        "to vary": "відрізнятись",
        "various": "різноманітний",
        "variable": "той, що відрізняється",
        "variety": "розмаїття",
        "of all ages": "всякого віку",
        "to learn to do sth.": "навчитись щось робити",
        "to get on with": "знаходити спільну мову з",
        "to adjust": "пристосовуватись",
        "different": "різний",
        "difference": "різниця",
        "to differ": "відрізнятись",
        "so far": "поки що",
        "to regret": "жалкувати",
        "to follow a career": "слідувати кар’єрою"
    },
    "6": {
        "to have a holiday": "проводити відпустку",
        "to take a holiday": "йти у відпустку",
        "to make up mind": "визначитись",
        "not really": "не зовсім",
        "somewhere": "десь",
        "to have a card": "отримати листівку",
        "to have a message": "отримати повідомлення",
        "to seem": "здаватись",
        "He seems to be having a good time": "Він здається гарно проводить час",
        "well-off": "заможний",
        "worse-off": "бідний",
        "that's o.k. for you well-off people": "добре вам багатіям",
        "possibly / probably / perhaps / maybe": "можливо",
        "to be hard up": "бути в скрутному становищі",
        "fare": "тариф",
        "air-fare": "плата за переліт",
        "to admit": "зізнаватись",
        "to do up": "ремонтувати (житло)",
        "to spare": "заощаджувати, відкладати",
        "expensive": "дорогий",
        "abroad": "за кордоном",
        "in the end / finally / after all / eventually": "в кінці кінців",
        "either of": "кожен з",
        "neither of": "жоден з",
        "to pay a visit": "провідати",
        "to call in on": "завітати",
        "willingly": "охоче",
        "reluctantly = unwillingly": "неохоче",
        "to put sb. up": "приймати когось в гості",
        "I'd like to …": "Я б хотів …",
        "How are you getting on?": "Як поживаєш?"
    },
    "7": {
        "tie": "краватка",
        "to tie a tie": "пов’язувати краватку",
        "a couple of": "пара",
        "to wear – wore – worn": "носити",
        "dinner party": "сімейна вечірка",
        "to look for": "шукати",
        "properly": "ретельно",
        "to expect": "очікувати",
        "to throw – threw – thrown": "жбурляти, кидати",
        "carelessly": "недбало",
        "back": "задня частина, спина",
        "wardrobe": "шафа для одягу, гардероб",
        "The way you usually do.": "Як ти зазвичай робиш.",
        "everywhere": "повсюди",
        "to tidy up": "прибирати",
        "to put things away": "розкладати речі по місцях",
        "to belong": "належати",
        "to blame": "звинувачувати",
        "to go out with": "виходити погуляти з",
        "to put on / take on": "одягати",
        "to put off / take off": "знімати",
        "to be in bed": "спати",
        "to remember": "пам’ятати",
        "a bit hot": "трохи спекотно",
        "to suppose": "припускати",
        "shelf": "поличка",
        "dashboard": "панель управління",
        "the shelf under the dashboard": "“бардачок”",
        "It's a good job": "Добре, що …",
        "firmly fixed": "міцно прикріплений",
        "shoulder": "плече",
        "otherwise": "інакше"
    },
    "9": {
        "road accident": "дтп",
        "to rain heavily": "падати (про сильний дощ)",
        "It was raining heavily.": "Падав сильний дощ.",
        "hill": "пагорб",
        "towards": "в напрямку до",
        "backwards": "в напрямку назад",
        "leftwards": "в напрямку ліворуч",
        "downwards": "в напрямку вниз",
        "traffic": "транспорт",
        "traffic lights (street lights)": "світлофор",
        "traffic jam": "затор на дорозі",
        "in sight": "в полі зору",
        "just as….": "якраз у ту мить",
        "top": "вершина",
        "bottom": "низ, дно",
        "to travel fast": "їхати на високій швидкості",
        "Obviously/apparently/evidently": "очевидно",
        "to have a difficulty in": "мати труднощі у",
        "difficult": "складний",
        "to control a car": "керувати авто",
        "to swerve": "рвонути",
        "violently": "жорстко",
        "to skid": "ковзати",
        "A car skidded on the wet road.": "Авто занесло на мокрій дорозі.",
        "lamp-post": "ліхтарний стовп",
        "to turn over": "перекинутись",
        "at once": "одразу",
        "to assist": "допомогти",
        "unconscious": "непритомний",
        "to hurry into": "поспіхом забігти в",
        "to phone for": "викликати (службу)",
        "to take care of sb.": "подбати про когось",
        "a number of people": "певна кількість людей",
        "to gather round sth.": "зібратись навколо чогось",
        "a great deal of sth.": "багато чогось (незчислюв.прийм.)",
        "shortly": "невдовзі",
        "afterwards": "після цього",
        "to come round": "опритомніти",
        "to groan": "стогнати (від болю)",
        "at high speed": "на високій швидкості",
        "to rush away to": "похапцем відвезти в",
        "to enquire (inquire)": "розпитуватись",
        "injury": "пошкодження/поранення",
        "rapidly": "швидко",
        "to get over": "одужувати",
        "the effects of sth.": "наслідки чогось."
    },
    "10": {
        "gossips": "плітки",
        "splendid": "чарівний, дивовижний",
        "to complain": "скаржитись",
        "to grumble": "нарікати",
        "heat": "спека",
        "to be satisfied": "бути задоволеним",
        "to satisfy": "задовольняти",
        "satisfactory": "задовільний",
        "satisfaction": "Задоволення, сатисфакція",
        "by the way": "до речі",
        "another": "інший (один)",
        "other": "інші (багато)",
        "badly hurt": "сильно поранений",
        "to come home from hospital": "виписуватися з лікарні",
        "to drive flat out": "їздити на високій швидкості порушуючи правила",
        "madly": "скажено, несамовито",
        "What wild things young men are these days!": "Яка несамовита молодь в наші дні!",
        "to get married": "одружуватися",
        "marriage": "шлюб",
        "Fancy that!": "Подумати тільки!",
        "dreadful habit": "шкідлива звичка",
        "dreadful person": "жахлива особа (характер)",
        "What a dreadful woman she is!": "Яка вона жахлива жінка!",
        "to last": "тривати, продовжуватись",
        "at this rate": "в такому темпі",
        "count": "рахунок (лічити)",
        "certainly": "точно"
    },
    "11": {
        "errand": "доручення",
        "as a matter of fact": "насправді",
        "let me see": "дай подумати",
        "cooking-fat": "смалець",
        "dozen": "дюжина",
        "jar": "глечик",
        "lard": "сало",
        "Hold on!": "Почекай!",
        "to write down": "записувати",
        "cupboard": "буфет",
        "wardrobe": "шафа для одягу",
        "bookcase": "книжкова шафа",
        "wall unit": "стінка (гарнітурна)",
        "to call in for": "зайти до когось для чогось",
        "To have a chat": "поговорити",
        "cocoa": "какао",
        "nearly = almost": "майже",
        "to run out of sth.": "закінчуватися",
        "instant coffee": "розчинна (кава)",
        "regular (ground) coffee": "натуральна (кава)",
        "Half a pound will do": "півфунта, буде достатньо",
        "to be short of sth.": "недостатність чогось, брак чогось",
        "stroll": "прогулянка",
        "lorry": "вантажівка",
        "Here’s the list": "ось список",
        "to pick up": "піднімати , забирати",
        "dry-cleaner’s": "хімчистка",
        "Do me a favour.": "Зроби мені послугу.",
        "do you mind if….": "ти не проти, якщо….",
        "to do business for sb.": "владнати чиїсь справи"
    },
    "13": {
        "to sit examinations": "готуватись до іспитів",
        "to be determined to": "визначитись, прийняти рішення",
        "to win a scholarship": "вибороти стипендію",
        "fortunately": "на щастя",
        "unfortunately": "нажаль",
        "to adore": "обожнювати",
        "in any case": "у будь якому випадку",
        "totally": "цілком, повністю",
        "to be bored with": "нудитись",
        "to be keen on": "бути помішаним на",
        "to loathe": "ненавидіти",
        "to oblige / make / force": "примушувати",
        "indoors": "зовні",
        "reasonable weather": "помірна погода",
        "reasonable prices": "помірні ціни",
        "several": "декілька",
        "tournament": "турнір",
        "to improve": "покращувати, вдосконалювати",
        "to practise": "тренуватись",
        "to approve": "схвалювати"
    },
    "14": {
        "prospect": "перспектива",
        "How have you been doing lately?": "Як у тебе справи останнім часом?",
        "terrible": "жахливий",
        "to be likely to": "скоріш за все",
        "to deserve": "заслуговувати",
        "He deserves to do well.": "Він заслуговує на краще.",
        "conscientious": "старанний",
        "hard-working": "працьовитий",
        "to slave at": "працювати як каторжник",
        "on end": "безупинно",
        "university lecturer": "викладач університету",
        "eventually": "в решті решт",
        "to enjoy oneself": "розважитись",
        "to have ability": "мати здібності",
        "inconsistent": "незібраний",
        "Rarely = seldom": "рідко",
        "to do one’s best": "старатись",
        "to make an effort": "прикладати зусиль",
        "idle": "лінивий",
        "to care less about sth.": "трошки чимсь перейнятись",
        "to be crazy about": "бути схибленим на",
        "to make fortune": "розбагатіти",
        "old-fashioned": "старомодний",
        "to make money": "заробляти гроші",
        "to give up": "здаватись, покидати",
        "to study law": "вивчати право",
        "to take up a career": "обирати кар’єру",
        "to be cut out for": "бути створеним для",
        "I wonder": "цікаво",
        "to develop": "розвиватись"
    },
    "15": {
        "to reckon": "вважати",
        "dead easy": "цілком легкий",
        "Come on!": "Припини!",
        "dead certain": "абсолютно переконаний",
        "to fail in": "зазнати невдачі",
        "most likely": "скоріш за все",
        "Thank goodness.": "Дякувати Богу!",
        "to be over": "закінчуватись",
        "to get on with": "продовжити з",
        "It's up to you.": "На твій розсуд.",
        "day off": "вихідний, відгул",
        "to get down to work": "всістись за роботу",
        "pretty soon": "дуже скоро",
        "to get through exams": "здавати іспити",
        "A level exams (Advanced)": "ЗНО",
        "O level exams (Ordinary)": "ДПА",
        "to swot": "зубрити",
        "I can't stand it.": "Я терпіти цього не можу.",
        "to join the army": "піти в армію",
        "to run away": "тікати"
    },
    "17": {
        "Informal": "неофіційний",
        "formal": "офіційний",
        "to let sb. know": "дати комусь знати",
        "to invite": "запрошувати",
        "house-warming party": "новосілля",
        "I'm sorry about the lack or warning": "Шкода, що не повідомили раніше.",
        "to move house": "переїжджати",
        "in any case": "в будь якому випадку",
        "to hold the party": "проводити вечірку",
        "to find out": "дізнатись",
        "as high as": "такий високий як",
        "cash": "готівка",
        "cash point": "банкомат",
        "ATM (automated telling machine)": "банкомат",
        "to spare": "заощаджувати",
        "to move in": "вселятись",
        "non-stop": "безупинно",
        "ever since": "весь час відтоді",
        "invitation": "запрошення",
        "motorway = highway": "магістраль",
        "rather": "доволі(з негативним значенням)",
        "housing estate": "житловий мікрорайон",
        "Give us a ring.": "Набери нас.",
        "area": "територія, район",
        "detailed directions": "детальні вказівки",
        "in spite of": "не зважаючи на",
        "short notice": "коротке повідомлення",
        "to fix sb. up": "забезпечити когось чимсь",
        "to imagine": "уявляти",
        "You can put up with it.": "Переб’єшся."
    },
    "18": {
        "so far": "поки що",
        "post-office": "поштове відділення",
        "crossroads": "перехрестя",
        "Carry on along the road.": "Продовжуй їхати вздовж дороги.",
        "steep hill": "крутий схил",
        "take the turning to the left": "скористайся поворотом ліворуч",
        "bottom": "дно",
        "top": "вершина",
        "just before the turning": "не доїжджаючи до повороту",
        "I've got that.": "Я второпав.",
        "to wind – wound – wound": "звиватись",
        "just after": "одразу після",
        "road fork": "дорожня виделка, рогатка",
        "Slow down a bit!": "Пригальмуй!",
        "as you come out of": "на виїзді з",
        "search party": "пошукова група"
    },
    "19": {
        "to arrange the house": "облаштовувати дім",
        "Give me a hand.": "Допоможи мені.",
        "sideboard": "стінка",
        "settee": "диванчик",
        "armchair": "м’яке крісло",
        "anyway": "у будь якому разі",
        "to hang – hung – hung": "вішати, висіти",
        "to be in the way": "заважати на шляху",
        "to arrange pictures": "розвішати картини",
        "furniture": "меблі",
        "screwdriver": "викрутка",
        "toolbox": "ящик з інструментами",
        "to tighten up": "прикрутити",
        "loose screws": "розхитані шурупи",
        "door hinges": "дверні завіси",
        "sink": "раковина",
        "to fetch": "захопити",
        "brush": "щітка",
        "tools": "інструменти",
        "polished table": "лакований столик",
        "to spoil – spoilt – spoilt": "псувати",
        "Don't keep on nagging.": "Не прискіпуйся.",
        "By the way.": "До речі.",
        "to get lost": "загубитись",
        "definitely": "точно",
        "fed up with": "ситий по горло",
        "fuss": "метушня",
        "to creep – crept – crept": "забиратись, заповзати",
        "cupboard": "буфет",
        "as well": "також"
    },
    "21": {
        "to sit around": "сидіти без діла",
        "to make a special effort": "прикласти особливих зусиль",
        "for ages": "роками",
        "to get round to": "взятись за",
        "to cut the garden hedge": "підстригти живопліт",
        "to dig the weeds out of the vegetable patch": "посапати грядки",
        "to dig – dug – dug": "копати",
        "weeds": "бур’ян",
        "vegetable patch": "грядка",
        "cabbages": "капуста",
        "onions": "цибуля",
        "to mow the lawn": "підстригти газон",
        "to polish the car": "натерти машину",
        "to give a car service": "оглянути авто",
        "badly": "терміново",
        "to take a car to the garage": "відвезти авто на сто",
        "labour costs": "плата за роботу",
        "nowadays": "в наші дні, нашими днями",
        "there's no point in": "немає сенсу у",
        "since": "оскільки",
        "to be at a loose end": "байдикувати",
        "in return": "натомість",
        "to go round to": "зайти",
        "Go round to us.": "Підтягуйтесь."
    },
    "22": {
        "fee": "гонорар",
        "brand new": "як нова копійка",
        "to adjust the clutch": "відрегулювати щеплення",
        "to check the brakes": "перевірити гальма",
        "spark plugs": "свічки запалювання",
        "We won't be long now.": "Тепер уже не довго.",
        "spanner": "гайковий ключ",
        "Here you are.": "Ось.",
        "front tyres": "передні шини",
        "back tyres": "задні шини",
        "to wear out": "зноситись",
        "to notice": "помітити",
        "to check the oil level": "перевірити рівень масла",
        "battery": "акумулятор",
        "to fill sth. up": "заповнити щось",
        "Get a move on.": "Рухайся.",
        "to start the engine": "заводити двигун",
        "What's up with it?": "Що з ним не так?",
        "over there": "он там",
        "to put sth. right": "владнати щось",
        "in a jiffy": "миттєво",
        "Go ahead.": "Починай.",
        "to disconnect": "від’єднати",
        "wire": "провід",
        "to change around": "поміняти місцями",
        "like this": "ось так"
    },
    "23": {
        "If you don't mind.": "Якщо ви не проти.",
        "suspect": "підозрюваний",
        "suspicious": "підозрілий",
        "to suspect": "підозрювати",
        "suspicion": "підозра",
        "By all means.": "Чим зможу, тим допоможу.",
        "murder": "вбивство",
        "to commit a crime": "скоїти злочин",
        "to commit a suicide": "вчинити самогубство",
        "next door": "по-сусідству",
        "out of the ordinary": "незвичний",
        "I was minding my own business.": "Я переймався власними справами.",
        "to fire a shot": "здійснити постріл",
        "revolver": "револьвер",
        "yet": "крім того",
        "to add": "додати",
        "You won't get away with it.": "Вам від цього не втекти.",
        "What was that?": "До чого б це?",
        "to proceed": "продовжувати",
        "enquiries": "допит"
    },
    "25": {
        "elections": "вибори",
        "to vote": "голосувати",
        "general election": "загальнонаціональні вибори",
        "shortly": "невдовзі",
        "seemingly": "здавалося б",
        "interminable": "нескінченний",
        "speech": "промова",
        "debates": "дебати",
        "under away": "повсюди",
        "labour party": "лейбористська партія",
        "to succeed": "досягнути успіху",
        "attempt": "спроба",
        "to increase": "збільшувати",
        "slender": "незначний",
        "majority": "більшість",
        "to introduce": "запроваджувати",
        "measures": "межі, рамки",
        "including": "включно",
        "widespread": "загальнопоширений",
        "private industry": "приватна промисловість",
        "in an effort": "у спробі",
        "to rescue": "рятувати",
        "threatening": "загрозливий",
        "to convince": "переконувати",
        "to encourage": "заохочувати",
        "private enterprise": "приватне підприємництво",
        "to unite": "об’єднатись",
        "government": "уряд",
        "to overcome": "подолати",
        "evil": "зло",
        "food shortage": "нестача їжі",
        "fuel crises": "паливна криза",
        "world-wide slump": "всесвітнє економічне падіння",
        "to persuade": "переконувати",
        "voter": "виборець",
        "to achieve": "досягнути",
        "prosperity": "процвітання",
        "leadership": "лідерство",
        "meanwhile": "тим часом",
        "to urge": "переконувати",
        "citizen": "громадянин",
        "complete independence": "повна незалежність",
        "parliament": "парламент"
    },
    "26": {
        "in luck": "повезло",
        "to get a transfer": "отримати перевід (по роботі)",
        "How did you manage that?": "Як тобі це вдалось?",
        "Who pulled strings for you?": "Хто замовив за тебе слово?",
        "I happened to be …": "Сталось так, що я був…",
        "to get by in": "вміти говорити (якоюсь мовою)",
        "to mention": "зазначити",
        "night school": "вечірня школа",
        "to set off": "відправитись",
        "to stay in hotel": "зупинитись в готелі",
        "ferry": "переправа",
        "Roll on monday then!": "Отож їдеш в понеділок!",
        "to head": "прямувати",
        "Mediterranean": "Середземномор’я",
        "to sweat": "пріти, пітніти",
        "correspondence": "кореспонденція, документація",
        "to pour with rain": "лити немов з відра",
        "Never mind.": "Не бери в голову",
        "Your turn will come.": "Твоя черга прийде.",
        "the Sahara Desert": "пустеля Сахара",
        "anyway": "як би там не було",
        "to envy": "заздрити",
        "to do overtime": "працювати наднормово",
        "to sort office out": "збирати речі (по роботі)",
        "Cheerio!": "цьомки-бомки)));)"
    },
    "27": {
        "to be looking forward to": "з нетерпінням чекати на",
        "I can't wait to…": "Я не можу дочекатись…",
        "to be scared stiff of": "бути до смерті наляканим",
        "journey": "подорож (як правило літаком)",
        "to insist on": "наполягати на",
        "to sail": "пливти (під вітрилами, кораблем)",
        "to make sb. nervous": "хвилювати когось",
        "frightened": "наляканий",
        "air crash": "авіакатастрофа",
        "road casualty": "ДТП",
        "per year": "на рік",
        "compared with": "у порівнянні з",
        "luxury = luxurious": "розкішний",
        "to be a good sailor": "добре переносити море",
        "rough sea": "бурхливе море",
        "boat": "човен",
        "sightseeing tour": "оглядовий тур",
        "to be sea-sick": "страждати морською хворобою",
        "sea-sickness": "морська хвороба"
    },
    "29": {
        "essential": "важливий, суттєвий",
        "to double": "подвоїти",
        "to resolve": "вирішувати",
        "except": "окрім",
        "necessary": "необхідний",
        "newsagent's": "газетний кіоск",
        "on foot": "пішки",
        "to economize": "економити",
        "to keep fit": "підтримувати форму",
        "It's all a question of habit!": "Це все питання звички!",
        "to rely on": "покладатись на",
        "besides": "окрім",
        "to catch a bus": "сісти на автобус",
        "in the country": "в селі",
        "frequently": "часто",
        "to and fro": "туди й назад",
        "gallon": "галон",
        "petrol": "бензин",
        "amount": "сума",
        "to get used to": "звикати",
        "to get accustomed to": "звикати",
        "to do without sth.": "обходитись без"
    },
    "30": {
        "helpful": "корисний",
        "ladder": "драбина",
        "to lend": "позичити (дати позику)",
        "to lean against": "сперти на",
        "to settle down": "обживатись",
        "You will feel at home soon.": "Ви скоро відчуєте себе як вдома.",
        "Do you mind if…": "Ви не проти якщо…",
        "to borrow": "позичити (взяти позику)",
        "drill": "дриль",
        "to drill holes": "свердлити дірки",
        "to put up shelves": "повісити полички",
        "to bore": "просвердлити",
        "to ruin": "зіпсувати, зламати",
        "It's child's play.": "Це – дитяча забавка.",
        "to plug in": "під’єднати до мережі",
        "to press a switch": "натиснути кнопку",
        "to release a switch": "відпустити кнопку",
        "out of stock": "немає в продажі",
        "hardware store": "магазин господарчих товарів",
        "Hang on!": "Почекай!",
        "Help yourself!": "Пригощайся!",
        "generous": "щедрий",
        "to oblige": "догодити"
    },
    "31": {
        "commuter": "житель передмістя (добирається на роботу в місто)",
        "How are things?": "Як справи?",
        "to involve": "залучати",
        "to bother": "надокучати",
        "Don't you find it a strain?": "Тобі не здається це напружливим?",
        "ghastly": "нестерпний",
        "dawn": "схід сонця",
        "dusk": "захід сонця",
        "to catch a train": "сісти на потяг",
        "bearable": "стерпний",
        "awful": "жахливий",
        "waste of time": "марна трата часу",
        "to pass the time": "проводити час",
        "to sit in comfort": "вмоститись",
        "to catch up with the news": "бути в курсі новин",
        "to have a nap": "подрімати (покуняти)",
        "on the train": "у потязі",
        "to bump into": "натрапити на",
        "entire": "весь",
        "You never know…": "Хтозна…"
    },
    "33": {
        "blunder": "груба помилка",
        "absentminded": "розсіяний",
        "short-sighted": "короткозорий",
        "mind": "розум",
        "learned thoughts": "вчені думки",
        "to notice": "помітити",
        "What is going on around?": "Що відбувається?",
        "in the countryside": "за містом / в селі",
        "no sooner he/she…": "не встиг він / вона",
        "to become engrossed in sth.": "бути захопленим чимсь",
        "to bump into": "наткнутись, наскочити",
        "massive": "масивний, великий",
        "to fall down": "впасти",
        "spectacles": "окуляри (для зору)",
        "in the fall": "в падінні",
        "to stumble over": "перечепитись",
        "I beg your pardon": "Перепрошую, пробачте",
        "to beg": "благати",
        "politely": "ввічливо",
        "to search": "здійснювати пошук",
        "as soon as": "як тільки",
        "to realize": "усвідомлювати",
        "to concentrate": "зосередитись",
        "to pay attention": "приділити увагу",
        "scarcely = hardly": "ледве",
        "glasses": "окуляри (будь які)",
        "furious": "розлючений",
        "to seize": "схопити",
        "to strike – struck – struck": "вдарити (предметом)",
        "in anger": "від злості",
        "with horror": "нажаханий",
        "to make a mistake": "здійснити помилку",
        "to flee – fled – fled": "тікати",
        "in terror": "переляканий"
    },
    "34": {
        "loyal": "лояльний, вірний",
        "dreadful": "жахливий",
        "exciting": "захоплюючий",
        "neither…nor…": "ні…ні…",
        "skilful": "досвідчений",
        "the weather didn't help": "погода була не на нашу користь",
        "to kick off": "розводити м’яч",
        "to pelt with rain": "періщити дощем",
        "useless": "безпорадний",
        "mud": "багнюка, болото",
        "to be off form": "бути не в формі",
        "conditions": "умови",
        "to be on form": "бути в формі",
        "I can't help laughing": "Я не можу не засміятись",
        "to watch": "спостерігати",
        "opposition": "супротивник",
        "I can't make out": "Я не можу второпати",
        "supporter": "вболівальник",
        "to tackle": "мотатись (боротись за м’яч)",
        "to get injured": "поранитись",
        "to be up to sth.": "мати щось спільне з",
        "defender": "захисник",
        "forward": "нападаючий",
        "management": "керівництво",
        "mean": "жадібний",
        "ground": "майданчик",
        "pitch": "поле (футбольне)",
        "disgrace": "ганьба",
        "flat": "плоский (рівний)",
        "drains": "дренаж",
        "to be covered with": "бути вкритим",
        "puddle of water": "калабаня",
        "promotion": "просування",
        "the third division": "третя ліга"
    },
    "35": {
        "to give up": "покинути, здатись",
        "to be asleep": "спати",
        "report": "звіт",
        "worn out": "виснажений",
        "to give the lesson a miss": "пропустити заняття",
        "to miss lessons": "прогулювати уроки",
        "to have a gift for": "мати талант для",
        "to laugh at": "сміятись з",
        "to attempt": "намагатись",
        "to assure": "запевняти",
        "to brush up": "освіжити",
        "to speak fluently": "розмовляти вільно (мовою)",
        "Keep it up!": "Так тримати!"
    },
    "37": {
        "auntie": "тітонька",
        "to be very sorry about": "дуже шкодувати через",
        "to be back in hospital": "знову потрапити до лікарні",
        "to be out and about": "бути в хорошому гуморі (одужати)",
        "according to": "згідно з",
        "in any case = anyway": "у будь якому випадку",
        "to recover": "одужувати",
        "to stay with sb.": "зупинитись в когось",
        "as soon as": "як тільки",
        "to get accustomed to": "звикатись",
        "to have some time to oneself": "приділити собі час",
        "peaceful": "мирний",
        "luckily = fortunately": "на щастя",
        "to object to": "протестувати проти, заперечувати",
        "on the contrary": "навпаки",
        "to appear": "виявлятись",
        "a little nearer": "дещо ближче",
        "to pray for": "молитись за",
        "to send love": "надсилати найкращі побажання",
        "speedy recovery": "швидке одужання",
        "to be looking forward to": "з нетерпінням чекати на"
    },
    "38": {
        "to be in a terrible hurry": "жахливо поспішати",
        "right away = straight away": "негайно",
        "to picking sb up": "захопити когось",
        "to promise": "обіцяти",
        "on time": "вчасно",
        "Gosh!": "О боже!",
        "It's not quite half past twelve yet.": "Зараз навіть не пів першої.",
        "It doesn't make any difference.": "Це не має значення.",
        "oven": "піч",
        "marvellous": "дивовижний",
        "to put smth by": "відкласти щось",
        "to starve": "зголодніти",
        "mushroom omelette": "омлет з грибами",
        "pork pie": "пиріг зі свинини",
        "stale": "черствий",
        "It's not much of a lunch.": "Це не зовсім схоже на обід.",
        "to race in and out": "гонити туди і назад",
        "within": "в межах",
        "magician": "маг",
        "to take pot luck": "задовільнитись тим що є",
        "arrangements": "організація",
        "warning": "застереження",
        "rotten restaurant": "«гнилий», (зіпсований) ресторан",
        "to complain": "скаржитись",
        "manager": "керівник",
        "food poisoning": "харчове отруєння",
        "to put sb in prison": "ув’язнити когось"
    },
    "39": {
        "season": "пора року",
        "chilly": "прохолодний",
        "all of a sudden": "раптово",
        "to be over": "закінчуватись",
        "certainly": "точно, звісно",
        "to draw in.": "затягуватись",
        "tea-time": "підвечірок",
        "to light the fires": "запалювати камін",
        "blazing": "виблискуючий",
        "coal": "вугілля",
        "I don't mind": "Я не проти",
        "as long as": "як тільки, оскільки",
        "cosy": "затишний",
        "to adore": "обожнювати",
        "crisp": "хруст",
        "I can't stand": "Терпіти не можу",
        "heat-wave": "спекотна хвиля",
        "to turn sour": "скиснути",
        "to grow older": "постарішати",
        "no doubt": "без сумніву",
        "to flash past": "минати миттєво",
        "oak tree": "дуб",
        "lane": "провулок",
        "to go grey": "посивіти",
        "Never mind.": "Не бери в голову.",
        "to go bald": "лисіти"
    }
}